[{
    "imageUrl": "https://www.atomy.com/in/shopping/p_img/100/00511_2.JPG",
    "title": "Compact Toothbrush 8N",
    "price": "1000.00"
  },
  {
    "imageUrl": "https://www.atomy.com/in/shopping/p_img/100/00510_2.jpg",
    "title": "Toothbrush 8N",
    "price": "1000.00"
  },
  {
    "imageUrl": "https://www.atomy.com/in/shopping/p_img/100/00620_2.jpg",
    "title": "Saengmodan Hair Tonic",
    "price": "1300.00"
  },
  {
    "imageUrl": "https://www.atomy.com/in/shopping/p_img/100/00521_2.jpg",
    "title": "Toothpaste 50g x 4 N",
    "price": "600.00"
  },
  {
    "imageUrl": "https://www.atomy.com/in/shopping/p_img/100/00183_2.jpg",
    "title": "Atomy Pomegranate Mixed Fruit Jelly",
    "price": "7500.00"
  },
  {
    "imageUrl": "https://www.atomy.com/in/shopping/p_img/100/00104_2.jpg",
    "title": "HemoHIM *4set",
    "price": "60000.00"
  },
  {
    "imageUrl": "https://www.atomy.com/in/shopping/p_img/100/90178_2.jpeg",
    "title": "ATOMY 100% PURE* SPIRULINA (India)",
    "price": "699.00"
  },
  {
    "imageUrl": "https://www.atomy.com/in/shopping/p_img/100/00833_2.jpeg",
    "title": "Latex Gloves(M) - 2 Pair",
    "price": "800.00"
  },
  {
    "imageUrl": "https://www.atomy.com/in/shopping/p_img/100/00281_2.jpeg",
    "title": "Sunscreen SPF50+ PA+++(Beige )",
    "price": "900.00"
  },
  {
    "imageUrl": "https://www.atomy.com/in/shopping/p_img/100/00003_2.jpeg",
    "title": "The Fame Skincare Set (5 Pcs per Set)",
    "price": "9100.00"
  },
  {
    "imageUrl": "https://www.atomy.com/in/shopping/p_img/100/00160_2.jpg",
    "title": "Atomy Nutraceutical Mix",
    "price": "4500.00"
  },
  {
    "imageUrl": "https://www.atomy.com/in/shopping/p_img/100/00475_2.jpg",
    "title": "Cerabebe 3set",
    "price": "4000.00"
  },
  {
    "imageUrl": "https://www.atomy.com/in/shopping/p_img/100/00351_2.jpeg",
    "title": "Evening Care Set(4 Pcs per Set)",
    "price": "3300.00"
  },
  {
    "imageUrl": "https://www.atomy.com/in/shopping/p_img/100/00267_2.png",
    "title": "Absolute Nutrition Cream",
    "price": "3300.00"
  },
  {
    "imageUrl": "https://www.atomy.com/in/shopping/p_img/100/00271_2.jpeg",
    "title": "Sunscreen SPF50+ PA+++(White )",
    "price": "900.00"
  },
  {
    "imageUrl": "https://www.atomy.com/in/shopping/p_img/100/00266_2.jpg",
    "title": "Healthy Glow Base SPF30 PA++",
    "price": "1400.00"
  },
  {
    "imageUrl": "https://www.atomy.com/in/shopping/p_img/100/00460_2.jpg",
    "title": "Lip Treatment",
    "price": "600.00"
  },
  {
    "imageUrl": "https://www.atomy.com/in/shopping/p_img/100/00826_2.jpg",
    "title": "Sheet Laundry Detergent",
    "price": "1600.00"
  },
  {
    "imageUrl": "https://www.atomy.com/in/shopping/p_img/100/00257_2.png",
    "title": "Absolute Eye-Complex",
    "price": "3700.00"
  },
  {
    "imageUrl": "https://www.atomy.com/in/shopping/p_img/100/00247_2.png",
    "title": "Absolute Lotion",
    "price": "3400.00"
  },
  {
    "imageUrl": "https://www.atomy.com/in/shopping/p_img/100/00237_2.png",
    "title": "Absolute Serum",
    "price": "3700.00"
  },
  {
    "imageUrl": "https://www.atomy.com/in/shopping/p_img/100/00217_2.png",
    "title": "Absolute Toner",
    "price": "3300.00"
  },
  {
    "imageUrl": "https://www.atomy.com/in/shopping/p_img/100/00645_2.jpg",
    "title": "Body Lotion",
    "price": "1200.00"
  },
  {
    "imageUrl": "https://www.atomy.com/in/shopping/p_img/100/00227_2.png",
    "title": "Absolute Ampoule",
    "price": "4500.00"
  }, {
    "imageUrl": "https://www.atomy.com/in/shopping/p_img/100/00835_2.jpg",
    "title": "Stainless Scrubber 2N",
    "price": "400.00"
  }, {
    "imageUrl": "https://www.atomy.com/in/shopping/p_img/100/00832_2.jpg",
    "title": "Scrubber 4N",
    "price": "600.00"
  }, {
    "imageUrl": "https://www.atomy.com/in/shopping/p_img/100/00693_2.jpg",
    "title": "Scalpcare 2 Set",
    "price": "2800.00"
  }, {
    "imageUrl": "https://www.atomy.com/in/shopping/p_img/100/00692_2.JPG",
    "title": "Scalpcare Hair Conditioner",
    "price": "1600.00"
  }, {
    "imageUrl": "https://www.atomy.com/in/shopping/p_img/100/00691_2.jpg",
    "title": "Scalpcare Hair Shampoo",
    "price": "1500.00"
  }, {
    "imageUrl": "https://www.atomy.com/in/shopping/p_img/100/00681_2.jpg",
    "title": "Hair Essential Oil",
    "price": "1300.00"
  }, {
    "imageUrl": "https://www.atomy.com/in/shopping/p_img/100/00661_2.JPG",
    "title": "Herbal Hair Conditioner",
    "price": "1400.00"
  }, {
    "imageUrl": "https://www.atomy.com/in/shopping/p_img/100/00651_2.jpg",
    "title": "Hair & Body Set (4 Pcs per Set)",
    "price": "4100.00"
  }, {
    "imageUrl": "https://www.atomy.com/in/shopping/p_img/100/00631_2.jpg",
    "title": "Herbal Body Cleanser",
    "price": "1000.00"
  }, {
    "imageUrl": "https://www.atomy.com/in/shopping/p_img/100/00861_2.jpg",
    "title": "Liquid Laundry Detergent",
    "price": "1300.00"
  }, {
    "imageUrl": "https://www.atomy.com/in/shopping/p_img/100/00611_2.jpg",
    "title": "Herbal Hair Treatment",
    "price": "800.00"
  }, {
    "imageUrl": "https://www.atomy.com/in/shopping/p_img/100/00755_2.jpeg",
    "title": "Hydra Brightening  capsule essence",
    "price": "1600.00"
  }, {
    "imageUrl": "https://www.atomy.com/in/shopping/p_img/100/00601_2.jpg",
    "title": "Herbal Hair Shampoo",
    "price": "1200.00"
  }, {
    "imageUrl": "https://www.atomy.com/in/shopping/p_img/100/00756_2.jpeg",
    "title": "Hydra Brightening  cream",
    "price": "1600.00"
  }, {
    "imageUrl": "https://www.atomy.com/in/shopping/p_img/100/00541_2.jpeg",
    "title": "Hand Soap",
    "price": "500.00"
  }, {
    "imageUrl": "https://www.atomy.com/in/shopping/p_img/100/04006_2.jpg",
    "title": "Atomy Algae Omega3",
    "price": "5800.00"
  }, {
    "imageUrl": "https://www.atomy.com/in/shopping/p_img/100/00520_2.jpg",
    "title": "Oral Care System*1set",
    "price": "1300.00"
  }, {
    "imageUrl": "https://www.atomy.com/in/shopping/p_img/100/00311_2.jpg",
    "title": "Evening Care Peeling Gel",
    "price": "900.00"
  }, {
    "imageUrl": "https://www.atomy.com/in/shopping/p_img/100/00331_2.JPG",
    "title": "Evening Care Peel Off Mask",
    "price": "900.00"
  }, {
    "imageUrl": "https://www.atomy.com/in/shopping/p_img/100/00321_2.jpg",
    "title": "Evening Care Deep Cleanser",
    "price": "900.00"
  }, {
    "imageUrl": "https://www.atomy.com/in/shopping/p_img/100/00301_2.jpg",
    "title": "Evening Care Foam Cleanser",
    "price": "900.00"
  }, {
    "imageUrl": "https://www.atomy.com/in/shopping/p_img/100/00261_2.jpg",
    "title": "BB Cream SPF30 PA++",
    "price": "900.00"
  }, {
    "imageUrl": "https://www.atomy.com/in/shopping/p_img/100/00198_2.jpg",
    "title": "The Fame Nutrition Cream",
    "price": "2000.00"
  }, {
    "imageUrl": "https://www.atomy.com/in/shopping/p_img/100/00196_2.jpg",
    "title": "The Fame Lotion",
    "price": "2000.00"
  }, {
    "imageUrl": "https://www.atomy.com/in/shopping/p_img/100/92680_2.jpeg",
    "title": "Atomy T-Shirt (S)-1N",
    "price": "378.00"
  }, {
    "imageUrl": "https://www.atomy.com/in/shopping/p_img/100/00194_2.jpg",
    "title": "The Fame Essence",
    "price": "2100.00"
  }, {
    "imageUrl": "https://www.atomy.com/in/shopping/p_img/100/92681_2.jpeg",
    "title": "Atomy T-Shirt (M)-1N",
    "price": "378.00"
  }, {
    "imageUrl": "https://www.atomy.com/in/shopping/p_img/100/00192_2.jpg",
    "title": "The Fame Eye Cream",
    "price": "2000.00"
  }, {
    "imageUrl": "https://www.atomy.com/in/shopping/p_img/100/92676_2.jpeg",
    "title": "Atomy T-Shirt (L)-1N",
    "price": "378.00"
  }, {
    "imageUrl": "https://www.atomy.com/in/shopping/p_img/100/00190_2.JPG",
    "title": "The Fame Toner",
    "price": "2000.00"
  }, {
    "imageUrl": "https://www.atomy.com/in/shopping/p_img/100/92677_2.jpeg",
    "title": "Atomy T-Shirt (XL)-1N",
    "price": "378.00"
  }, {
    "imageUrl": "https://www.atomy.com/in/shopping/p_img/100/92682_2.jpeg",
    "title": "Atomy T-Shirt (XXL)-1N",
    "price": "378.00"
  }, {
    "imageUrl": "https://www.atomy.com/in/shopping/p_img/100/92688_2.jpg",
    "title": "Atomy Pamphlet Food & Health Products only (100 pcs per pack)",
    "price": "200.00"
  }, {
    "imageUrl": "https://www.atomy.com/in/shopping/p_img/100/92658_2.jpeg",
    "title": "Atomy Life Scenario (Including Moment of Truth)",
    "price": "150.00"
  }, {
    "imageUrl": "https://www.atomy.com/in/shopping/p_img/100/92619_2.jpg",
    "title": "Hindi Pamphlet Foldable- Version 2023 (25 pcs per pack)",
    "price": "200.00"
  }, {
    "imageUrl": "https://www.atomy.com/in/shopping/p_img/100/92618_2.jpg",
    "title": "English Pamphlet Foldable- Version 2023 (25 pcs per pack)",
    "price": "200.00"
  }, {
    "imageUrl": "https://www.atomy.com/in/shopping/p_img/100/92453_2.jpg",
    "title": "Mini Catalog 10 Pcs-(English)- Version January 2023",
    "price": "500.00"
  }, {
    "imageUrl": "https://www.atomy.com/in/shopping/p_img/100/92445_2.jpeg",
    "title": "Shopping Bag(Non Woven)",
    "price": "28.00"
  }, {
    "imageUrl": "https://www.atomy.com/in/shopping/p_img/100/04718_2.jpg",
    "title": "Adelica Waterproof Mascara - Brown",
    "price": "1000.00"
  }, {
    "imageUrl": "https://www.atomy.com/in/shopping/p_img/100/04717_2.jpg",
    "title": "Adelica Waterproof Mascara - Black",
    "price": "1000.00"
  }, {
    "imageUrl": "https://www.atomy.com/in/shopping/p_img/100/02479_2.jpg",
    "title": "ATOMY DNA (ENGLISH)",
    "price": "850.00"
  }, {
    "imageUrl": "https://www.atomy.com/in/shopping/p_img/100/01443_2.jpg",
    "title": "Synergy Ampoule Program *1 set",
    "price": "8500.00"
  }, {
    "imageUrl": "https://www.atomy.com/in/shopping/p_img/100/01235_2.jpg",
    "title": "Atomy Homme Energizing All In One",
    "price": "2000.00"
  }, {
    "imageUrl": "https://www.atomy.com/in/shopping/p_img/100/00975_2.jpg",
    "title": "Atomy Cafe Arabica Black (50 sticks)",
    "price": "2000.00"
  }, {
    "imageUrl": "https://www.atomy.com/in/shopping/p_img/100/00965_2.png",
    "title": "Atomy Balance Life",
    "price": "7500.00"
  }, {
    "imageUrl": "https://www.atomy.com/in/shopping/p_img/100/00871_2.jpg",
    "title": "Fabric Softener",
    "price": "1500.00"
  }, {
    "imageUrl": "https://www.atomy.com/in/shopping/p_img/100/00838_2.jpg",
    "title": "Atomy 365 Anti Droplet Face Mask (50 sheet)",
    "price": "3200.00"
  }, {
    "imageUrl": "https://www.atomy.com/in/shopping/p_img/100/00828_2.jpg",
    "title": "Fabric Detergent (1KG)",
    "price": "800.00"
  }, {
    "imageUrl": "https://www.atomy.com/in/shopping/p_img/100/00808_2.jpg",
    "title": "Atomy Anti Pollution Mask [KF94]  (5 pcs)",
    "price": "800.00"
  }, {
    "imageUrl": "https://www.atomy.com/in/shopping/p_img/100/00801_2.jpg",
    "title": "Atomy Dishwashing Liquid",
    "price": "1200.00"
  }, {
    "imageUrl": "https://www.atomy.com/in/shopping/p_img/100/00757_2.jpg",
    "title": "Hydra Brightening Care Set (2 Pcs per Set)",
    "price": "3000.00"
  }, {
    "imageUrl": "https://www.atomy.com/in/shopping/p_img/100/00553_2.JPG",
    "title": "Cleansing Travel Kit (6pcs per set)",
    "price": "1500.00"
  }, {
    "imageUrl": "https://www.atomy.com/in/shopping/p_img/100/00467_2.jpg",
    "title": "Atomy Daily Expert Mask Firming",
    "price": "1300.00"
  }, {
    "imageUrl": "https://www.atomy.com/in/shopping/p_img/100/00466_2.jpg",
    "title": "Atomy Daily Expert Mask  Brightening",
    "price": "1300.00"
  }, {
    "imageUrl": "https://www.atomy.com/in/shopping/p_img/100/00465_2.jpg",
    "title": "Atomy Daily Expert Mask Moisturizing",
    "price": "1300.00"
  }, {
    "imageUrl": "https://www.atomy.com/in/shopping/p_img/100/00295_2.jpg",
    "title": "Atomy Rose Rain Mist",
    "price": "1400.00"
  }, {
    "imageUrl": "https://www.atomy.com/in/shopping/p_img/100/00286_2.jpg",
    "title": "Atomy Sun Stick",
    "price": "1200.00"
  }, {
    "imageUrl": "https://www.atomy.com/in/shopping/p_img/100/00180_2.jpg",
    "title": "Atomy Pu'er Tea",
    "price": "3600.00"
  }, {
    "imageUrl": "https://www.atomy.com/in/shopping/p_img/100/00174_2.jfif",
    "title": "Atomy Milk Thistle",
    "price": "3800.00"
  }, {
    "imageUrl": "https://www.atomy.com/in/shopping/p_img/100/00170_2.png",
    "title": "Atomy Noni Drink",
    "price": "6500.00"
  }, {
    "imageUrl": "https://www.atomy.com/in/shopping/p_img/100/00101_2.jpg",
    "title": "HemoHIM *1set",
    "price": "15000.00"
  }
]